davis_weatherlink_scraper/__init__.py
davis_weatherlink_scraper-0.1.0.data/scripts/weatherlink
davis_weatherlink_scraper-0.1.0.data/scripts/weatherlink_redis_publisher
davis_weatherlink_scraper-0.1.0.dist-info/DESCRIPTION.rst
davis_weatherlink_scraper-0.1.0.dist-info/METADATA
davis_weatherlink_scraper-0.1.0.dist-info/RECORD
davis_weatherlink_scraper-0.1.0.dist-info/WHEEL
davis_weatherlink_scraper-0.1.0.dist-info/metadata.json
davis_weatherlink_scraper-0.1.0.dist-info/top_level.txt
